mtpkg/__init__.py
mtpkg/cli.py
mtpkg/local.py
mtpkg/remote.py
mtpkg-0.2.0.dist-info/LICENSE
mtpkg-0.2.0.dist-info/METADATA
mtpkg-0.2.0.dist-info/WHEEL
mtpkg-0.2.0.dist-info/entry_points.txt
mtpkg-0.2.0.dist-info/top_level.txt
mtpkg-0.2.0.dist-info/RECORD
