Metadata-Version: 2.1
Name: mtpkg
Version: 0.2.0
Summary: Command-line Minetest package manager
Home-page: https://sr.ht/~twrightsman/mtpkg
Author: Travis Wrightsman
Author-email: travis@wrightsman.org
License: AGPLv3+
Project-URL: Bug Tracker, https://todo.sr.ht/~twrightsman/mtpkg
Project-URL: Source, https://git.sr.ht/~twrightsman/mtpkg
Keywords: utilities,games
Platform: UNKNOWN
Classifier: Programming Language :: Python :: 3 :: Only
Classifier: Development Status :: 3 - Alpha
Classifier: Environment :: Console
Classifier: License :: OSI Approved :: GNU Affero General Public License v3 or later (AGPLv3+)
Classifier: Topic :: Utilities
Classifier: Typing :: Typed
Requires-Python: >=3.7
Requires-Dist: requests (<3,>=2)
Requires-Dist: click (<8,>=7)
Requires-Dist: tqdm (<5,>=4)
Requires-Dist: appdirs (<2,>=1)
